README.md
setup.py
async_cse/__init__.py
async_cse/search.py
async_cse.egg-info/PKG-INFO
async_cse.egg-info/SOURCES.txt
async_cse.egg-info/dependency_links.txt
async_cse.egg-info/requires.txt
async_cse.egg-info/top_level.txt