Metadata-Version: 2.1
Name: async-cse
Version: 0.3.0
Summary: API wrapper for the Google Custom Search JSON API. https://developers.google.com/custom-search/v1/overview
Home-page: https://github.com/crrapi/async-cse
Author: crrapi
License: MIT
Platform: UNKNOWN
Classifier: Programming Language :: Python :: 3.5
Classifier: Programming Language :: Python :: 3.6
Classifier: Programming Language :: Python :: 3.7
Classifier: License :: OSI Approved :: MIT License
Classifier: Operating System :: OS Independent
